thonnycontrib/skriware/__init__.py
thonnycontrib/skriware/boot.png
thonnycontrib/skriware/debug.png
thonnycontrib/skriware/foo.png
thonnycontrib/skriware/help.py
thonnycontrib/skriware/restart.png
thonnycontrib/skriware/robot.png
thonnycontrib/skriware/scratchpad.png
thonnycontrib/skriware/select.png
thonnycontrib/skriware/settings.json
thonnycontrib/skriware/shell.py
thonnycontrib/skriware/skriware_plugin.py
thonnycontrib/skriware/stop.png
thonnycontrib/skriware/theme.py
thonnycontrib/skriware/upload.png
thonnycontrib/skriware/upload.py
thonnycontrib/skriware/icons/boot.png
thonnycontrib/skriware/icons/debug.png
thonnycontrib/skriware/icons/foo.png
thonnycontrib/skriware/icons/help.png
thonnycontrib/skriware/icons/restart.png
thonnycontrib/skriware/icons/robot.png
thonnycontrib/skriware/icons/scratchpad.png
thonnycontrib/skriware/icons/select.png
thonnycontrib/skriware/icons/stop.png
thonnycontrib/skriware/icons/upload.png
thonnycontrib/skriware/micropython-skribot/boot.py
thonnycontrib/skriware/micropython-skribot/claw.py
thonnycontrib/skriware/micropython-skribot/dc_rotor.py
thonnycontrib/skriware/micropython-skribot/distance_sensor.py
thonnycontrib/skriware/micropython-skribot/example_avoid_obstacles.py
thonnycontrib/skriware/micropython-skribot/example_functions.py
thonnycontrib/skriware/micropython-skribot/example_line_follower.py
thonnycontrib/skriware/micropython-skribot/firmware.bin
thonnycontrib/skriware/micropython-skribot/led.py
thonnycontrib/skriware/micropython-skribot/line_sensor.py
thonnycontrib/skriware/micropython-skribot/scratchpad.py
thonnycontrib/skriware/micropython-skribot/servo.py
thonnycontrib/skriware/micropython-skribot/skribot.py
thonnycontrib/skriware/micropython-skribot/skribrain.py
thonnycontrib/skriware/micropython-skribot/skribrain3.py
thonny_skriware-0.1.3.dist-info/LICENSE
thonny_skriware-0.1.3.dist-info/METADATA
thonny_skriware-0.1.3.dist-info/WHEEL
thonny_skriware-0.1.3.dist-info/top_level.txt
thonny_skriware-0.1.3.dist-info/RECORD
